MANIFEST.in
node_config
setup.py
django_node_websockets.egg-info/PKG-INFO
django_node_websockets.egg-info/SOURCES.txt
django_node_websockets.egg-info/dependency_links.txt
django_node_websockets.egg-info/pbr.json
django_node_websockets.egg-info/requires.txt
django_node_websockets.egg-info/top_level.txt
websockets/__init__.py
websockets/models.py
websockets/settings.py
websockets/setup.py
websockets/urls.py
websockets/utils.py
websockets/views.py
websockets/management/__init__.py
websockets/management/commands/__init__.py
websockets/management/commands/broadcast.py
websockets/migrations/0001_initial.py
websockets/migrations/__init__.py
websockets/scripts/app.js
websockets/scripts/config-sample.js
websockets/south_migrations/0001_initial.py
websockets/south_migrations/__init__.py