Metadata-Version: 1.0
Name: django-node-websockets
Version: 0.1.18
Summary: Websockets
Home-page: UNKNOWN
Author: John Leith
Author-email: leith.john@gmail.com
License: UNKNOWN
Platform: UNKNOWN
